protocolmodel/__about__.py
protocolmodel/__init__.py
protocolmodel/http.py
protocolmodel-0.0.1b2.dist-info/METADATA
protocolmodel-0.0.1b2.dist-info/WHEEL
protocolmodel-0.0.1b2.dist-info/RECORD
