Metadata-Version: 2.3
Name: protocolmodel
Version: 0.0.1b2
Summary: Protocol model 
Author: liqzz
License-Expression: MIT
Classifier: Programming Language :: Python
Classifier: Programming Language :: Python :: 3.11
Classifier: Programming Language :: Python :: 3.12
Classifier: Programming Language :: Python :: Implementation :: CPython
Classifier: Programming Language :: Python :: Implementation :: PyPy
Requires-Python: >=3.10
Requires-Dist: pydantic
Requires-Dist: werkzeug
